tezos_python/__init__.py
tezos_python/client/__init__.py
tezos_python/client/client.py
tezos_python/client/client_output.py
tezos_python/daemons/__init__.py
tezos_python/daemons/baker.py
tezos_python/daemons/endorser.py
tezos_python/daemons/node.py
tezos_python/daemons/utils.py
tezos_python/launchers/__init__.py
tezos_python/launchers/sandbox.py
tezos_python/scripts/__init__.py
tezos_python/scripts/build_branches.py
tezos_python/scripts/run_node_baker.py
tezos_python/tools/__init__.py
tezos_python/tools/constants.py
tezos_python/tools/paths.py
tezos_python/tools/utils.py
tezos_python-0.0.3.data/scripts/run_node
tezos_python-0.0.3.data/scripts/run_node_baker.py
tezos_python-0.0.3.dist-info/LICENSE
tezos_python-0.0.3.dist-info/METADATA
tezos_python-0.0.3.dist-info/WHEEL
tezos_python-0.0.3.dist-info/top_level.txt
tezos_python-0.0.3.dist-info/RECORD
